kvcheetah/__init__.py
kvcheetah/__main__.py
kvcheetah/data/__init__.py
kvcheetah/data/images/sprites-0.png
kvcheetah/data/images/sprites.atlas
kvcheetah/data/images/tiles-0.png
kvcheetah/data/images/tiles.atlas
kvcheetah/data/sfx/bubble-pop.wav
kvcheetah/graphics/__init__.py
kvcheetah/graphics/sprite.cp38-win_amd64.pyd
kvcheetah/graphics/tilemap.cp38-win_amd64.pyd
kvcheetah/graphics/opengl/__init__.py
kvcheetah/math/__init__.py
kvcheetah/math/matrix.cp38-win_amd64.pyd
kvcheetah/math/vector.cp38-win_amd64.pyd
kvcheetah/uix/__init__.py
kvcheetah/uix/joystick.cp38-win_amd64.pyd
kvcheetah-2.0.1.dist-info/LICENSE
kvcheetah-2.0.1.dist-info/METADATA
kvcheetah-2.0.1.dist-info/WHEEL
kvcheetah-2.0.1.dist-info/top_level.txt
kvcheetah-2.0.1.dist-info/RECORD
