Metadata-Version: 2.1
Name: kvcheetah
Version: 2.0.1
Summary: A lightweight game engine based on Kivy.
Home-page: https://github.com/Cybermals/kvcheetah
Author: Eric Snyder
Author-email: cybermals.group@gmail.com
License: MIT
Platform: macosx_10_15_x86_64
Platform: manylinux1_x86_64
Platform: win_amd64
Classifier: Development Status :: 4 - Beta
Classifier: Programming Language :: Python :: 3
Classifier: License :: OSI Approved :: MIT License
Classifier: Operating System :: Android
Classifier: Operating System :: MacOS
Classifier: Operating System :: Microsoft :: Windows
Classifier: Operating System :: Unix
Classifier: Topic :: Games/Entertainment
Classifier: Topic :: Multimedia :: Graphics
